sageodata_db/__init__.py
sageodata_db/config.py
sageodata_db/connection.py
sageodata_db/utils.py
sageodata_db/queries/all_aquifer_units.sql
sageodata_db/queries/all_drillholes.sql
sageodata_db/queries/all_mound_spring_conditions.sql
sageodata_db/queries/all_mound_springs.sql
sageodata_db/queries/all_replacement_drillholes.sql
sageodata_db/queries/all_strat_units.sql
sageodata_db/queries/aquifer_units.sql
sageodata_db/queries/aquifers_monitored.sql
sageodata_db/queries/casing_seals.sql
sageodata_db/queries/casing_strings.sql
sageodata_db/queries/chem_codes.sql
sageodata_db/queries/construction_events.sql
sageodata_db/queries/data_available.sql
sageodata_db/queries/data_edits_aquifer_mon.sql
sageodata_db/queries/drilled_intervals.sql
sageodata_db/queries/drillers_logs.sql
sageodata_db/queries/drillhole_by_dh_seq_no.sql
sageodata_db/queries/drillhole_by_obs_seq_no.sql
sageodata_db/queries/drillhole_construction_by_permit_nos.sql
sageodata_db/queries/drillhole_current_monitoring_networks.sql
sageodata_db/queries/drillhole_current_sal_monitoring_networks.sql
sageodata_db/queries/drillhole_current_wl_monitoring_networks.sql
sageodata_db/queries/drillhole_details.sql
sageodata_db/queries/drillhole_details_all.sql
sageodata_db/queries/drillhole_details_by_latest_permit.sql
sageodata_db/queries/drillhole_details_by_lon_lat_rect.sql
sageodata_db/queries/drillhole_details_by_name_search.sql
sageodata_db/queries/drillhole_details_by_pwa.sql
sageodata_db/queries/drillhole_details_by_pwra.sql
sageodata_db/queries/drillhole_details_by_utm_rect.sql
sageodata_db/queries/drillhole_document_image_list.sql
sageodata_db/queries/drillhole_document_references.sql
sageodata_db/queries/drillhole_file_list.sql
sageodata_db/queries/drillhole_groups.sql
sageodata_db/queries/drillhole_image_list.sql
sageodata_db/queries/drillhole_image_list_with_image_contents.sql
sageodata_db/queries/drillhole_logs.sql
sageodata_db/queries/drillhole_no_by_obs_no.sql
sageodata_db-0.47.1.dist-info/LICENSE
sageodata_db-0.47.1.dist-info/METADATA
sageodata_db-0.47.1.dist-info/WHEEL
sageodata_db-0.47.1.dist-info/top_level.txt
sageodata_db-0.47.1.dist-info/RECORD
