Metadata-Version: 2.1
Name: sageodata_db
Version: 0.47.1
Summary: SA Geodata database querying tool/wrapper/library
Home-page: https://github.com/dew-waterscience/sageodata_db
Author: DEW Water Science (Kent Inverarity)
Author-email: groundwater@sa.gov.au
License: All rights reserved
Keywords: science
Classifier: Programming Language :: Python :: 3
License-File: LICENSE
Requires-Dist: oracledb
Requires-Dist: pandas
Requires-Dist: python-sa-gwdata
Requires-Dist: sqlparse
Requires-Dist: pillow
Requires-Dist: pyautogui
